LICENSE
MANIFEST.in
README.rst
setup.py
motuz/__init__.py
motuz.egg-info/PKG-INFO
motuz.egg-info/SOURCES.txt
motuz.egg-info/dependency_links.txt
motuz.egg-info/requires.txt
motuz.egg-info/top_level.txt