Metadata-Version: 1.1
Name: motuz
Version: 0.0.2
Summary: a web based infrastructure for large scale data movements between on-premise and cloud 
Home-page: https://github.com/FredHutch/motuz
Author: Dirk Petersen
Author-email: dp@nowhere.com
License: UNKNOWN
Download-URL: https://github.com/FredHutch/motuz/tarball/0.0.2
Keywords: hpc,scientific computing
Platform: UNKNOWN
Classifier: Development Status :: 3 - Alpha
Classifier: Intended Audience :: Developers
Classifier: Intended Audience :: Science/Research
Classifier: Intended Audience :: System Administrators
Classifier: License :: OSI Approved :: Apache Software License
Classifier: Natural Language :: English
Classifier: Operating System :: POSIX :: Linux
Classifier: Programming Language :: Python :: 3
Classifier: Programming Language :: Python :: 3.5
Classifier: Programming Language :: Python :: 3.6
Classifier: Programming Language :: Python :: 3.7
Classifier: Programming Language :: Python :: 3.8
Classifier: Programming Language :: Python :: Implementation :: CPython
Classifier: Programming Language :: Unix Shell
Classifier: Topic :: Software Development :: Libraries :: Python Modules
Classifier: Topic :: System :: Systems Administration
Classifier: Topic :: Utilities
